{
  "src/routes/+layout.css": {
    "file": "_app/immutable/assets/_layout-5f863472.css",
    "src": "src/routes/+layout.css"
  },
  "src/routes/+error.css": {
    "file": "_app/immutable/assets/_error-9d93381c.css",
    "src": "src/routes/+error.css"
  },
  "src/routes/blog/[slug]/+layout.css": {
    "file": "_app/immutable/assets/_layout-9790b95d.css",
    "src": "src/routes/blog/[slug]/+layout.css"
  },
  "3x3-grid.css": {
    "file": "_app/immutable/assets/3x3-grid-c71ee51f.css",
    "src": "3x3-grid.css"
  },
  "src/routes/blog/+page.css": {
    "file": "_app/immutable/assets/_page-01e86fca.css",
    "src": "src/routes/blog/+page.css"
  },
  "section.css": {
    "file": "_app/immutable/assets/section-81f95976.css",
    "src": "section.css"
  },
  "src/routes/resume/+page.css": {
    "file": "_app/immutable/assets/_page-c7f09232.css",
    "src": "src/routes/resume/+page.css"
  },
  "src/routes/+page.css": {
    "file": "_app/immutable/assets/_page-9ad66961.css",
    "src": "src/routes/+page.css"
  },
  "src/routes/+layout.ts": {
    "file": "_app/immutable/modules/pages/_layout.ts-5612100c.js",
    "src": "src/routes/+layout.ts",
    "isEntry": true,
    "imports": [
      "__layout-79cb23d1.js"
    ]
  },
  ".svelte-kit/generated/nodes/6.js": {
    "file": "_app/immutable/chunks/6-fb20067b.js",
    "src": ".svelte-kit/generated/nodes/6.js",
    "isDynamicEntry": true,
    "imports": [
      "src/routes/resume/+page.svelte"
    ]
  },
  ".svelte-kit/generated/nodes/5.js": {
    "file": "_app/immutable/chunks/5-5dd4aabe.js",
    "src": ".svelte-kit/generated/nodes/5.js",
    "isDynamicEntry": true,
    "imports": [
      "src/routes/blog/[slug]/+page.svelte"
    ]
  },
  ".svelte-kit/generated/nodes/1.js": {
    "file": "_app/immutable/chunks/1-cd6c7d49.js",
    "src": ".svelte-kit/generated/nodes/1.js",
    "isDynamicEntry": true,
    "imports": [
      "src/routes/+error.svelte"
    ]
  },
  ".svelte-kit/generated/nodes/2.js": {
    "file": "_app/immutable/chunks/2-a84550f3.js",
    "src": ".svelte-kit/generated/nodes/2.js",
    "isDynamicEntry": true,
    "imports": [
      "src/routes/blog/[slug]/+layout.svelte"
    ]
  },
  ".svelte-kit/generated/nodes/3.js": {
    "file": "_app/immutable/chunks/3-8be4caff.js",
    "src": ".svelte-kit/generated/nodes/3.js",
    "isDynamicEntry": true,
    "imports": [
      "src/routes/+page.svelte"
    ]
  },
  ".svelte-kit/generated/nodes/0.js": {
    "file": "_app/immutable/chunks/0-f77a7591.js",
    "src": ".svelte-kit/generated/nodes/0.js",
    "isDynamicEntry": true,
    "imports": [
      "__layout-79cb23d1.js",
      "src/routes/+layout.svelte"
    ]
  },
  ".svelte-kit/generated/nodes/4.js": {
    "file": "_app/immutable/chunks/4-ebbd2391.js",
    "src": ".svelte-kit/generated/nodes/4.js",
    "isDynamicEntry": true,
    "imports": [
      "src/routes/blog/+page.svelte"
    ]
  },
  "_3x3-grid-3fcfac94.js": {
    "file": "_app/immutable/chunks/3x3-grid-3fcfac94.js",
    "imports": [
      "_index-2e64fc78.js"
    ],
    "css": [
      "_app/immutable/assets/3x3-grid-c71ee51f.css"
    ]
  },
  "src/routes/blog/[slug]/+page.svelte": {
    "file": "_app/immutable/components/pages/blog/_slug_/_page.svelte-d8e2cfbf.js",
    "src": "src/routes/blog/[slug]/+page.svelte",
    "isEntry": true,
    "imports": [
      "_index-2e64fc78.js"
    ]
  },
  "_meta-7c4229da.js": {
    "file": "_app/immutable/chunks/meta-7c4229da.js"
  },
  "__layout-79cb23d1.js": {
    "file": "_app/immutable/chunks/_layout-79cb23d1.js"
  },
  "_index-2e64fc78.js": {
    "file": "_app/immutable/chunks/index-2e64fc78.js"
  },
  "node_modules/@sveltejs/kit/src/runtime/client/start.js": {
    "file": "_app/immutable/start-4304d6d6.js",
    "src": "node_modules/@sveltejs/kit/src/runtime/client/start.js",
    "isEntry": true,
    "imports": [
      "_index-2e64fc78.js"
    ],
    "dynamicImports": [
      ".svelte-kit/generated/nodes/0.js",
      ".svelte-kit/generated/nodes/1.js",
      ".svelte-kit/generated/nodes/2.js",
      ".svelte-kit/generated/nodes/3.js",
      ".svelte-kit/generated/nodes/4.js",
      ".svelte-kit/generated/nodes/5.js",
      ".svelte-kit/generated/nodes/6.js"
    ]
  },
  "src/routes/+layout.svelte": {
    "file": "_app/immutable/components/pages/_layout.svelte-91f17331.js",
    "src": "src/routes/+layout.svelte",
    "isEntry": true,
    "imports": [
      "_index-2e64fc78.js",
      "_meta-7c4229da.js"
    ],
    "css": [
      "_app/immutable/assets/_layout-5f863472.css"
    ]
  },
  "src/routes/+error.svelte": {
    "file": "_app/immutable/components/pages/_error.svelte-42cc7915.js",
    "src": "src/routes/+error.svelte",
    "isEntry": true,
    "imports": [
      "_index-2e64fc78.js"
    ],
    "css": [
      "_app/immutable/assets/_error-9d93381c.css"
    ]
  },
  "src/routes/blog/[slug]/+layout.svelte": {
    "file": "_app/immutable/components/pages/blog/_slug_/_layout.svelte-39b0249b.js",
    "src": "src/routes/blog/[slug]/+layout.svelte",
    "isEntry": true,
    "imports": [
      "_index-2e64fc78.js",
      "_section-7dc61734.js",
      "_3x3-grid-3fcfac94.js",
      "_meta-7c4229da.js"
    ],
    "css": [
      "_app/immutable/assets/_layout-9790b95d.css"
    ]
  },
  "_section-7dc61734.js": {
    "file": "_app/immutable/chunks/section-7dc61734.js",
    "imports": [
      "_index-2e64fc78.js"
    ],
    "css": [
      "_app/immutable/assets/section-81f95976.css"
    ]
  },
  "src/routes/blog/+page.svelte": {
    "file": "_app/immutable/components/pages/blog/_page.svelte-76837fff.js",
    "src": "src/routes/blog/+page.svelte",
    "isEntry": true,
    "imports": [
      "_index-2e64fc78.js",
      "_section-7dc61734.js"
    ],
    "css": [
      "_app/immutable/assets/_page-01e86fca.css"
    ]
  },
  "src/routes/resume/+page.svelte": {
    "file": "_app/immutable/components/pages/resume/_page.svelte-b1df2fd3.js",
    "src": "src/routes/resume/+page.svelte",
    "isEntry": true,
    "imports": [
      "_index-2e64fc78.js",
      "_meta-7c4229da.js"
    ],
    "css": [
      "_app/immutable/assets/_page-c7f09232.css"
    ]
  },
  "src/routes/+page.svelte": {
    "file": "_app/immutable/components/pages/_page.svelte-fc76eada.js",
    "src": "src/routes/+page.svelte",
    "isEntry": true,
    "imports": [
      "_index-2e64fc78.js",
      "_section-7dc61734.js",
      "_3x3-grid-3fcfac94.js"
    ],
    "css": [
      "_app/immutable/assets/_page-9ad66961.css"
    ]
  }
}